kapfinance/__init__.py
kapfinance/kapfinance.py
kapfinance-0.1.3.dist-info/licenses/LICENSE
kapfinance-0.1.3.dist-info/METADATA
kapfinance-0.1.3.dist-info/WHEEL
kapfinance-0.1.3.dist-info/top_level.txt
kapfinance-0.1.3.dist-info/RECORD
