Metadata-Version: 2.4
Name: kapfinance
Version: 0.1.3
Summary: A Python class for managing financial statement data from HTML-based XLS files.
Home-page: https://github.com/mertkurtcu/kapfinance
Author: Mert Kurtçu
Author-email: mertkurtcu.official@gmail.com.com
Keywords: financial data manager,financial statements,balance sheet,income statement,html xls,pandas
Classifier: Programming Language :: Python :: 3
Classifier: License :: OSI Approved :: MIT License
Classifier: Operating System :: OS Independent
Classifier: Development Status :: 3 - Alpha
Classifier: Intended Audience :: Developers
Classifier: Intended Audience :: Financial and Insurance Industry
Classifier: Topic :: Office/Business :: Financial
Classifier: Topic :: Software Development :: Libraries :: Python Modules
Requires-Python: >=3.8
License-File: LICENSE
Requires-Dist: pandas>=1.0.0
Requires-Dist: numpy>=1.18.0
Requires-Dist: matplotlib>=3.0.0
Requires-Dist: lxml
Requires-Dist: openpyxl
Dynamic: author
Dynamic: author-email
Dynamic: classifier
Dynamic: description
Dynamic: description-content-type
Dynamic: home-page
Dynamic: keywords
Dynamic: license-file
Dynamic: requires-dist
Dynamic: requires-python
Dynamic: summary
